flask_mailgun.py
Flask_MailGun3-0.1.2.dist-info/DESCRIPTION.rst
Flask_MailGun3-0.1.2.dist-info/METADATA
Flask_MailGun3-0.1.2.dist-info/RECORD
Flask_MailGun3-0.1.2.dist-info/WHEEL
Flask_MailGun3-0.1.2.dist-info/metadata.json
Flask_MailGun3-0.1.2.dist-info/top_level.txt
