Metadata-Version: 2.0
Name: Flask-MailGun3
Version: 0.1.2
Summary: Flask extension to use the Mailgun email parsing service
Home-page: https://github.com/amey-sam/Flask-MailGun
Author: Amey-SAM
Author-email: richard.mathie@amey.co.uk
License: MIT
Download-URL: https://github.com/amey-sam/Flask-MailGun/tarball/master
Keywords: flask,mailgun
Platform: any
Classifier: Development Status :: 4 - Beta
Classifier: Environment :: Web Environment
Classifier: Intended Audience :: Developers
Classifier: License :: OSI Approved :: MIT License
Classifier: Operating System :: OS Independent
Classifier: Programming Language :: Python
Classifier: Programming Language :: Python :: 2.7
Classifier: Topic :: Internet :: WWW/HTTP :: Dynamic Content
Classifier: Topic :: Software Development :: Libraries :: Python Modules
Requires-Dist: Flask
Requires-Dist: decorator
Requires-Dist: requests
